GBComments.py
data/__init__.py
data/data.py
GBComments-0.0.16.dist-info/LICENSE
GBComments-0.0.16.dist-info/METADATA
GBComments-0.0.16.dist-info/WHEEL
GBComments-0.0.16.dist-info/top_level.txt
GBComments-0.0.16.dist-info/RECORD
