Metadata-Version: 2.1
Name: GBComments
Version: 0.0.16
Summary: 用于生成好评差评的库
Home-page: https://github.com/WRAllen/GBComments
Author: WRAllen
Author-email: 1072274105@qq.com
License: UNKNOWN
Platform: UNKNOWN
